LICENSE
MANIFEST.in
README.md
dev_requirements.txt
requirements.txt
setup.cfg
setup.py
versioneer.py
csirtg_fm/__init__.py
csirtg_fm/_version.py
csirtg_fm/cli.py
csirtg_fm/constants.py
csirtg_fm.egg-info/PKG-INFO
csirtg_fm.egg-info/SOURCES.txt
csirtg_fm.egg-info/dependency_links.txt
csirtg_fm.egg-info/entry_points.txt
csirtg_fm.egg-info/requires.txt
csirtg_fm.egg-info/top_level.txt
csirtg_fm/archiver/__init__.py
csirtg_fm/archiver/constants.py
csirtg_fm/archiver/indicator.py
csirtg_fm/archiver/noop.py
csirtg_fm/clients/__init__.py
csirtg_fm/clients/apwg.py
csirtg_fm/clients/cif.py
csirtg_fm/clients/cifzmq.py
csirtg_fm/clients/constants.py
csirtg_fm/clients/csirtg.py
csirtg_fm/clients/http.py
csirtg_fm/content/__init__.py
csirtg_fm/content/utils.py
csirtg_fm/parsers/__init__.py
csirtg_fm/parsers/csv.py
csirtg_fm/parsers/delim.py
csirtg_fm/parsers/json.py
csirtg_fm/parsers/pattern.py
csirtg_fm/parsers/pipe.py
csirtg_fm/parsers/rss.py
csirtg_fm/parsers/semicolon.py
csirtg_fm/parsers/tsv.py
csirtg_fm/utils/__init__.py
csirtg_fm/utils/columns.py
csirtg_fm/utils/decoders.py
csirtg_fm/utils/indicator.py
csirtg_fm/utils/rules.py
test/test_cli.py