Metadata-Version: 1.1
Name: csirtg-fm
Version: 2.0b2
Summary: CSIRTG FM Framework
Home-page: https://github.com/csirtgadgets/csirtg-fm-v2
Author: Wes Young
Author-email: wes@csirtgadgets.com
License: MPL2
Keywords: security
Platform: UNKNOWN
Classifier: Topic :: System :: Networking
Classifier: Programming Language :: Python
